{"text":"San Ginese Asylum","color":"WHITE"}|
{"text":"Via dei piedini","color":"WHITE"}|
{"text":"Anatroccoli","color":"WHITE"}|
{"text":"Il calice della sborra","color":"WHITE"}|
{"text":"L'allergia alle noccioline di Giulietta","color":"WHITE"}|
{"text":"Sennar SUPER muscoloso","color":"WHITE"}|
{"text":"Arachidi geneticamente modificati","color":"WHITE"}|
{"text":"Giulia in monociclo","color":"WHITE"}|
{"text":"Il Clowntopus","color":"WHITE"}|
{"text":"Ape Zero","color":"WHITE"}|
{"text":"Giulia ma è un cavallo","color":"WHITE"}|
{"text":"Cyber Zero","color":"WHITE"}|
{"text":"Sterminio di uomini","color":"WHITE"}|
{"text":"Le katane di Michele e Sennar ","color":"WHITE"}|
{"text":"Instaurazione del matriarcato","color":"WHITE"}|
{"text":"La signora Fusi che schiavizza Alberto","color":"WHITE"}|
{"text":"Moon allupato al 30%","color":"WHITE"}|
{"text":"Antidepressivi coi piedini","color":"WHITE"}|
{"text":"Patto suicida","color":"WHITE"}|
{"text":"Infestando la Germania","color":"WHITE"}|
{"text":"La mano robotica di Giulietta","color":"WHITE"}|
{"text":"Liff quando ancora era minorenne","color":"WHITE"}|
{"text":"Jacopo il Buddhista","color":"WHITE"}|
{"text":"La panetteria","color":"WHITE"}|
{"text":"San Ginese Asylum","color":"WHITE"}|
{"text":"Via dei piedini","color":"WHITE"}|
{"text":"La figa mutante di Godzilla","color":"WHITE"}|
{"text":"Giulietta furiosa alla guida di un camion","color":"WHITE"}|
{"text":"La fursona di Filippo","color":"WHITE"}|
{"text":"Pisela","color":"WHITE"}|
{"text":"Emanu'el, l'orrore cosmico","color":"WHITE"}